{"cameraMode":{"drawMode":0,"name":"Shaded","section":"Shading Mode"},"sceneLighting":true,"audioPlay":false,"sceneViewState":{"m_AlwaysRefresh":false,"showFog":true,"showSkybox":true,"showFlares":true,"showImageEffects":true,"showParticleSystems":true,"showVisualEffectGraphs":true,"m_FxEnabled":true},"in2DMode":false,"pivot":{"x":21.979368209838868,"y":-13.581037521362305,"z":-32.0643196105957},"rotation":{"x":0.05871906131505966,"y":0.9414147138595581,"z":-0.2318602353334427,"w":0.23814526200294496},"size":20.588359832763673,"orthographic":false}